{
  "@context": "https://schema.org",
  "@graph": [
    {
      "@type": "Product",
      "name": "TOXFREE\u00ae XTREM LSZH H07ZZ-F (AS)",
      "mpn": "H07ZZ-F",
      "sku": "H07ZZ-F",
      "description": "Le c\u00e2ble en caoutchouc LSHF extra-flexible pour le service mobile. SELON: EN 50525-3-21. Le c\u00e2ble TOXFREE\u00ae XTREM LSZH H07ZZ-F (AS) est un c\u00e2ble flexible pour service mobile, adapt\u00e9 aux installations o\u00f9 une faible \u00e9mission de fum\u00e9e et d'halog\u00e8ne dans des conditions d'incendie est requise. La tension nominale d'utilisation jusqu'\u00e0 1000 V est accept\u00e9e dans les montages fixes prot\u00e9g\u00e9s. Convient aux installations o\u00f9 le c\u00e2ble doit r\u00e9sister \u00e0 des contraintes m\u00e9caniques moyennes, pour les machines dans les ateliers industriels et agricoles, pour les moteurs et les machines transportables sur les chantiers de construction, pour les \u00e9oliennes et pour les applications agricoles.",
      "image": [
        "https://www.topcable.com/wp-content/uploads/2025/07/topcable-toxfree-xtrem-lszh-h07zz-f-extra-flexible-lszh-rubber-cable-for-mobile-service-01.png",
        "https://www.topcable.com/wp-content/uploads/2025/07/TOPCABLE_TOXFREE_XTREM.webp",
        "https://www.topcable.com/wp-content/uploads/2025/07/bobina_negra.png"
      ],
      "url": "https://www.topcable.com/fr/cable/toxfree-lszh-xtrem-h07zz-f/",
      "category": "Hardware > Building Materials > Wiring & Cables > Electrical Cables",
      "brand": {
        "@type": "Brand",
        "name": "TOXFREE\u00ae",
        "url": "https://www.topcable.com/company/our-brands/"
      },
      "manufacturer": {
        "@type": "Organization",
        "@id": "https://www.topcable.com/#organization"
      },
      "material": "Copper, class 5 (flexible)",
      "audience": {
        "@type": "BusinessAudience",
        "audienceType": "Electrical Distributors, Electrical Installers, Engineers (Industrial Projects)"
      },
      "subjectOf": {
        "@type": "DigitalDocument",
        "name": "Fiche Technique - TOXFREE\u00ae XTREM LSZH H07ZZ-F (AS)",
        "url": "https://www.topcable.com/downloads/pdf/fr/topcable-datasheet-toxfree-lszh-xtrem-h07zz-f-fr.pdf",
        "encodingFormat": "application/pdf",
        "description": "Sp\u00e9cifications techniques compl\u00e8tes, donn\u00e9es d'ing\u00e9nierie et certifications du c\u00e2ble."
      },
      "additionalProperty": [
        {
          "@type": "PropertyValue",
          "name": "Conductor",
          "value": "Cuivre \u00e9lectrolytique, classe 5 (souple) selon EN 60228 et IEC 60228",
          "url": "https://www.electropedia.org/iev/iev.nsf/display?openform&ievref=151-12-05"
        },
        {
          "@type": "PropertyValue",
          "name": "Insulation",
          "value": "Caoutchouc thermodurcissable sans halog\u00e8ne, type EI8 selon EN 50363-5"
        },
        {
          "@type": "PropertyValue",
          "name": "Outer Sheath",
          "value": "Caoutchouc flexible thermodurcissable sans halog\u00e8ne, type EM8 selon EN 50363-6. Couleur noire."
        },
        {
          "@type": "PropertyValue",
          "name": "Rated Voltage",
          "value": "450/750",
          "unitText": "V"
        },
        {
          "@type": "PropertyValue",
          "name": "Maximum Conductor Temperature",
          "value": "90",
          "unitText": "\u00b0C"
        },
        {
          "@type": "PropertyValue",
          "name": "Maximum Short-Circuit Temperature",
          "value": "250 (max. 5 s)",
          "unitText": "\u00b0C"
        },
        {
          "@type": "PropertyValue",
          "name": "Minimum Service Temperature",
          "value": "-40 (installations fixes et prot\u00e9g\u00e9es)",
          "unitText": "\u00b0C"
        },
        {
          "@type": "PropertyValue",
          "name": "Flame Non-Propagation",
          "value": "Non propagation de la flamme selon EN 60332-1 / IEC 60332-1"
        },
        {
          "@type": "PropertyValue",
          "name": "Fire Non-Propagation",
          "value": "Non propagation de l'incendie selon EN 60332-3-24 / IEC 60332-3-24 et EN 50399"
        },
        {
          "@type": "PropertyValue",
          "name": "CPR Classification",
          "value": "B2ca-s1b, d1, a1 ou Cca-s1b, d2, a1 (selon section transversale) selon EN 50575"
        },
        {
          "@type": "PropertyValue",
          "name": "Halogen Free",
          "value": "Sans halog\u00e8ne selon EN 60754-1 / IEC 60754-1"
        },
        {
          "@type": "PropertyValue",
          "name": "Low Corrosive Gases Emission",
          "value": "Faible \u00e9mission de gaz corrosifs selon UNE-EN 60754-2 / IEC 60754-2"
        },
        {
          "@type": "PropertyValue",
          "name": "Low Smoke Emission",
          "value": "Faible \u00e9mission de fum\u00e9e selon EN 61034 / IEC 61034"
        },
        {
          "@type": "PropertyValue",
          "name": "Light Transmittance",
          "value": "> 60%"
        },
        {
          "@type": "PropertyValue",
          "name": "Minimum Bending Radius",
          "value": "3x diam\u00e8tre du c\u00e2ble < 12 mm ; 4x diam\u00e8tre du c\u00e2ble \u2265 12 mm"
        },
        {
          "@type": "PropertyValue",
          "name": "Impact Resistance",
          "value": "AG2 Gravit\u00e9 moyenne"
        },
        {
          "@type": "PropertyValue",
          "name": "Chemical & Oil Resistance",
          "value": "Excellente"
        },
        {
          "@type": "PropertyValue",
          "name": "Water Resistance",
          "value": "AD7 Immersion"
        },
        {
          "@type": "PropertyValue",
          "name": "Installation Conditions",
          "value": "\u00c0 l'air libre. En canalisation."
        },
        {
          "@type": "PropertyValue",
          "name": "Standards (According To)",
          "value": "EN 50525-3-21"
        },
        {
          "@type": "PropertyValue",
          "name": "Standards and Approvals",
          "value": "HAR, AENOR, CE"
        },
        {
          "@type": "PropertyValue",
          "name": "Typical Applications",
          "value": "Utilisation industrielle, Utilisation mobile, \u00c9oliennes"
        },
        {
          "@type": "PropertyValue",
          "name": "European Stock",
          "value": "Largest European Stock Holding"
        },
        {
          "@type": "PropertyValue",
          "name": "Manufacturing Quality",
          "value": "As cable manufacturers, we ensure cost-effective premium quality and lasting performance."
        },
        {
          "@type": "PropertyValue",
          "name": "Quality Testing",
          "value": "Our in-house labs guarantee rigorous cable quality, reliability, and standards compliance."
        },
        {
          "@type": "PropertyValue",
          "name": "Global Logistics",
          "value": "Global cable delivery solutions\u2014expert logistics for seamless supply."
        },
        {
          "@type": "PropertyValue",
          "name": "Fast Delivery",
          "value": "Full cable stock, ready for fast delivery- shortest lead times."
        },
        {
          "@type": "PropertyValue",
          "name": "Sustainability",
          "value": "EPD-certified cables: Sustainable manufacturing for your Scope 3 success."
        },
        {
          "@type": "PropertyValue",
          "name": "Customer Service",
          "value": "Expert, friendly and professional sales team offering a fast & efficient customer service. Global customers are welcome!"
        }
      ],
      "offers": {
        "@type": "Offer",
        "url": "https://www.topcable.com/fr/cable/toxfree-lszh-xtrem-h07zz-f/",
        "priceCurrency": "EUR",
        "price": 0,
        "availability": "https://schema.org/InStock",
        "itemCondition": "https://schema.org/NewCondition",
        "eligibleRegion": {
          "@type": "Place",
          "name": "World"
        },
        "seller": {
          "@type": "Organization",
          "@id": "https://www.topcable.com/#organization"
        }
      }
    },
    {
      "@type": "BreadcrumbList",
      "itemListElement": [
        {
          "@type": "ListItem",
          "position": 1,
          "name": "Accueil",
          "item": "https://www.topcable.com/fr/"
        },
        {
          "@type": "ListItem",
          "position": 2,
          "name": "C\u00e2bles LSZH",
          "item": "https://www.topcable.com/fr/cables-lszh/"
        },
        {
          "@type": "ListItem",
          "position": 3,
          "name": "TOXFREE\u00ae XTREM LSZH H07ZZ-F (AS)"
        }
      ]
    },
    {
      "@type": "Organization",
      "@id": "https://www.topcable.com/#organization",
      "name": "Top Cable",
      "url": "https://www.topcable.com/",
      "email": "sales@topcable.com",
      "telephone": "+34 935 880 911",
      "address": {
        "@type": "PostalAddress",
        "streetAddress": "Carrer de Leonardo da Vinci, 1",
        "addressLocality": "Rub\u00ed",
        "addressRegion": "Barcelona",
        "postalCode": "08191",
        "addressCountry": "ES"
      },
      "logo": {
        "@type": "ImageObject",
        "@id": "https://www.topcable.com/#logo",
        "url": "https://www.topcable.com/wp-content/uploads/2026/01/top-cable-logo.png",
        "contentUrl": "https://www.topcable.com/wp-content/uploads/2026/01/top-cable-logo.png"
      },
      "sameAs": [
        "https://www.linkedin.com/company/topcable/",
        "https://www.youtube.com/@Topcable_europe",
        "https://www.instagram.com/topcable_spain/",
        "https://www.facebook.com/topcable/"
      ]
    }
  ]
}